LICENSE
pytest_django_class/__init__.py
pytest_django_class-0.0.1.dist-info/LICENSE
pytest_django_class-0.0.1.dist-info/METADATA
pytest_django_class-0.0.1.dist-info/WHEEL
pytest_django_class-0.0.1.dist-info/RECORD
